quickframe.py
quickframe-0.1.0.dist-info/LICENSE
quickframe-0.1.0.dist-info/METADATA
quickframe-0.1.0.dist-info/WHEEL
quickframe-0.1.0.dist-info/entry_points.txt
quickframe-0.1.0.dist-info/RECORD
