Metadata-Version: 2.3
Name: quickframe
Version: 0.1.0
Summary: Lightning-fast video frame extraction tool - Part of QuickKit
License: MIT
Keywords: video,frames,extraction,quickkit,multimedia,performance,fast,opencv
Author: LoboGuardian 🐺
Author-email: loboguardian.dev@gmail.com
Requires-Python: >=3.11
Classifier: Development Status :: 3 - Alpha
Classifier: Intended Audience :: Developers
Classifier: Topic :: Multimedia :: Video
Classifier: Topic :: Software Development :: Libraries :: Python Modules
Classifier: License :: OSI Approved :: MIT License
Classifier: Programming Language :: Python :: 3
Classifier: Programming Language :: Python :: 3.11
Classifier: Programming Language :: Python :: 3.12
Classifier: Programming Language :: Python :: 3.13
Classifier: Programming Language :: Python :: 3.14
Requires-Dist: opencv-python (>=4.8.0)
Project-URL: Documentation, https://quickkit.github.io/quickframe
Project-URL: Homepage, https://github.com/quickkit/quickframe
Project-URL: Issues, https://github.com/quickkit/quickframe/issues
Project-URL: Organization, https://github.com/quickkit
Project-URL: Repository, https://github.com/quickkit/quickframe
